bmlgraphapi/__init__.py
bmlgraphapi/main.py
bmlgraphapi-0.5.dist-info/METADATA
bmlgraphapi-0.5.dist-info/WHEEL
bmlgraphapi-0.5.dist-info/top_level.txt
bmlgraphapi-0.5.dist-info/RECORD
