Metadata-Version: 2.1
Name: bmlgraphapi
Version: 0.5
Summary: Pacote para obter tabelas xlsx do SharePoint através de seu link
Author-email: Brenda Moura <brendamoura@bemol.com.br>
Keywords: xlsx,sharepoint,tabela,dataframe,dados,graphapi,microsoft
Requires-Python: >=3.8
Requires-Dist: msal
Requires-Dist: requests
Requires-Dist: openpyxl
Requires-Dist: pandas
